{
  "_fv": 18,
  "_type": "achievement",
  "definition": {
    "achievementName": "Going to the Poop World",
    "achievementDescription": "Go to the Poop Dimention",
    "achievementIcon": {
      "value": "CUSTOM:PoopwoodLeaves"
    },
    "background": "Default",
    "disableDisplay": false,
    "showPopup": true,
    "announceToChat": true,
    "hideIfNotCompleted": false,
    "rewardLoot": [],
    "rewardRecipes": [],
    "rewardFunction": "No function",
    "rewardXP": 1,
    "achievementType": "task",
    "parent": {
      "value": "CUSTOM:Poopblocj2"
    },
    "triggerxml": "<xml xmlns=\"https://developers.google.com/blockly/xml\"><block type=\"dimension_entered\" x=\"101\" y=\"123\"><field name=\"dimension\">CUSTOM:Poopdimension</field><next><block type=\"advancement_trigger\" deletable=\"false\"></block></next></block></xml>"
  }
}